claviz_python_api.py
claviz_python_api-0.0.8.dist-info/METADATA
claviz_python_api-0.0.8.dist-info/WHEEL
claviz_python_api-0.0.8.dist-info/top_level.txt
claviz_python_api-0.0.8.dist-info/RECORD
