Metadata-Version: 2.1
Name: claviz-python-api
Version: 0.0.8
Summary: Python API wrapper for Claviz.
Requires-Python: >=3.7
